{
  "version": 2,
  "extractor": "papercropper",
  "tables": [
    {
      "url": "assets/tables/openreview/openreview-icml-2025-pnz3piokrn/table-001.webp",
      "caption": "",
      "page": 0,
      "index": 1,
      "width": 1472,
      "height": 406,
      "label": "Table"
    },
    {
      "url": "assets/tables/openreview/openreview-icml-2025-pnz3piokrn/table-002.webp",
      "caption": "",
      "page": 0,
      "index": 2,
      "width": 869,
      "height": 242,
      "label": "Table"
    },
    {
      "url": "assets/tables/openreview/openreview-icml-2025-pnz3piokrn/table-003.webp",
      "caption": "",
      "page": 0,
      "index": 3,
      "width": 842,
      "height": 235,
      "label": "Table"
    },
    {
      "url": "assets/tables/openreview/openreview-icml-2025-pnz3piokrn/table-004.webp",
      "caption": "",
      "page": 0,
      "index": 4,
      "width": 1789,
      "height": 306,
      "label": "Table"
    },
    {
      "url": "assets/tables/openreview/openreview-icml-2025-pnz3piokrn/table-005.webp",
      "caption": "",
      "page": 0,
      "index": 5,
      "width": 871,
      "height": 127,
      "label": "Table"
    },
    {
      "url": "assets/tables/openreview/openreview-icml-2025-pnz3piokrn/table-006.webp",
      "caption": "",
      "page": 0,
      "index": 6,
      "width": 845,
      "height": 139,
      "label": "Table"
    },
    {
      "url": "assets/tables/openreview/openreview-icml-2025-pnz3piokrn/table-007.webp",
      "caption": "",
      "page": 0,
      "index": 7,
      "width": 532,
      "height": 235,
      "label": "Table"
    },
    {
      "url": "assets/tables/openreview/openreview-icml-2025-pnz3piokrn/table-008.webp",
      "caption": "",
      "page": 0,
      "index": 8,
      "width": 714,
      "height": 144,
      "label": "Table"
    }
  ]
}